routingpy/__init__.py
routingpy/__version__.py
routingpy/client_base.py
routingpy/client_default.py
routingpy/convert.py
routingpy/direction.py
routingpy/exceptions.py
routingpy/expansion.py
routingpy/isochrone.py
routingpy/matrix.py
routingpy/utils.py
routingpy/valhalla_attributes.py
routingpy/routers/__init__.py
routingpy/routers/google.py
routingpy/routers/graphhopper.py
routingpy/routers/heremaps.py
routingpy/routers/mapbox_osrm.py
routingpy/routers/mapbox_valhalla.py
routingpy/routers/openrouteservice.py
routingpy/routers/osrm.py
routingpy/routers/valhalla.py
routingpy-1.2.1.dist-info/AUTHORS.md
routingpy-1.2.1.dist-info/LICENSE
routingpy-1.2.1.dist-info/METADATA
routingpy-1.2.1.dist-info/WHEEL
routingpy-1.2.1.dist-info/top_level.txt
routingpy-1.2.1.dist-info/RECORD
