Metadata-Version: 2.1
Name: routingpy
Version: 1.2.1
Summary: One lib to route them all.
Home-page: https://github.com/gis-ops/routing-py
Author: Nils Nolde
Author-email: nils@gis-ops.com
License: Apache 2.0
Classifier: License :: OSI Approved :: Apache Software License
Classifier: Programming Language :: Python
Classifier: Programming Language :: Python :: 3
Classifier: Programming Language :: Python :: 3.7
Classifier: Programming Language :: Python :: 3.8
Classifier: Programming Language :: Python :: 3.9
Classifier: Programming Language :: Python :: 3.10
Classifier: Programming Language :: Python :: Implementation :: CPython
Classifier: Programming Language :: Python :: Implementation :: PyPy
Requires-Python: >=3.7.0
License-File: LICENSE
License-File: AUTHORS.md
Requires-Dist: requests (>=2.20.0)
